airtablecache/__init__.py
airtablecache/airtablecache.py
airtablecache/data/testData.csv
airtablecache-0.0.1.dist-info/LICENSE
airtablecache-0.0.1.dist-info/METADATA
airtablecache-0.0.1.dist-info/WHEEL
airtablecache-0.0.1.dist-info/top_level.txt
airtablecache-0.0.1.dist-info/RECORD
