Metadata-Version: 2.1
Name: airtablecache
Version: 0.0.1
Summary: Utility Package for Caching Data From Airtable
Home-page: https://github.com/raunakk/airtablecache
Author: Raunak Khandelwal
Author-email: raunakkhandelwal2000@yahoo.com
License: MIT
Platform: UNKNOWN
Classifier: Programming Language :: Python :: 3
Classifier: License :: OSI Approved :: MIT License
Classifier: Operating System :: OS Independent
Requires-Python: >=3.6
Requires-Dist: xlrd
Requires-Dist: numpy
Requires-Dist: pandas
Requires-Dist: gspread
Requires-Dist: gspread-dataframe
Requires-Dist: requests
Requires-Dist: airtable-python-wrapper
